hardware/hdl/src/alu.vhdl
library IEEE;
use IEEE.std_logic_1164.all;
use IEEE.numeric_std.all;

use work.CommonPkg.all;

entity ALU is
  port (
    X: in std_logic_vector(15 downto 0);
    Y: in std_logic_vector(15 downto 0);
    OP: in std_logic_vector(1 downto 0);
    ZX: in std_logic;
    ZY: in std_logic;
    NO: in std_logic;

    result: out std_logic_vector(15 downto 0);
    IsNeg: out std_logic;
    IsZero: out std_logic
  );
end entity ALU;

architecture rtl of ALU is
  signal opcode : opcode_type;
  signal intermediate_result: Word;
begin
  opcode <= to_opcode(OP);

  IsNeg <= intermediate_result(15);

  result <= intermediate_result;

  process(X, Y, OP, ZX, ZY, NO)
  begin
    case opcode is
      when ADD    => intermediate_result <= std_logic_vector(signed(X) + signed(Y));
      when SUB    => intermediate_result <= std_logic_vector(signed(X) - signed(Y));
      when AND_OP => intermediate_result <= X and Y;
      when OR_OP  => intermediate_result <= X or Y;
    end case;
    if intermediate_result = x"0000" then
      IsZero <= '1';
    else
      IsZero <= '0';
    end if;
  end process;
end architecture rtl;

hardware/hdl/src/alu_tb.vhdl
library IEEE;
use IEEE.std_logic_1164.all;
use IEEE.numeric_std.all;

use work.CommonPkg.all;
-- Testbench entity: No ports are needed for a testbench
entity ALU_tb is
end entity;

architecture Behavioral of ALU_tb is
  -- Test signals
  signal X, Y, result: std_logic_vector(15 downto 0);
  signal OP: std_logic_vector(1 downto 0);
  signal ZX, ZY, NO, IsNeg, IsZero: std_logic;

  -- Constants for the ALU operations (assuming they are 2-bit control codes)
  constant ADD    : std_logic_vector(1 downto 0) := "00";
  constant SUB    : std_logic_vector(1 downto 0) := "01";
  constant AND_OP : std_logic_vector(1 downto 0) := "10";
  constant OR_OP  : std_logic_vector(1 downto 0) := "11";

begin
  -- Instantiate the ALU component
  uut: entity work.ALU(rtl)
    port map(
      X => X,
      Y => Y,
      OP => OP,
      ZX => ZX,
      ZY => ZY,
      NO => NO,
      result => result,
      IsNeg => IsNeg,
      IsZero => IsZero
    );

  -- Test process
  process
  begin
    -- Test 1: ADD X and Y
    X <= x"0001";  -- X = 1
    Y <= x"0002";  -- Y = 2
    OP <= ADD;     -- Addition operation
    ZX <= '0';     -- No zeroing of X
    ZY <= '0';     -- No zeroing of Y
    NO <= '0';     -- Normal operation
    wait for 10 ns;

    -- Test 2: SUB X - Y
    OP <= SUB;
    wait for 10 ns;

    -- Test 3: AND X and Y
    OP <= AND_OP;
    wait for 10 ns;

    -- Test 4: OR X and Y
    OP <= OR_OP;
    wait for 10 ns;

    -- Test 5: Zero X and perform ADD
    ZX <= '1';     -- Zero X
    OP <= ADD;
    wait for 10 ns;

    -- Test 6: Zero Y and perform ADD
    ZX <= '0';     -- Restore X
    ZY <= '1';     -- Zero Y
    OP <= ADD;
    wait for 10 ns;

    -- Test 7: Apply NO signal (inverts result)
    NO <= '1';     -- Invert result
    OP <= ADD;
    wait for 10 ns;

    -- Test 8: Negative result (SUB test)
    X <= x"0002";
    Y <= x"0004";
    OP <= SUB;
    NO <= '0';     -- Normal operation
    wait for 10 ns;

    -- Test 9: Test IsZero
    X <= x"0000";
    Y <= x"0000";
    OP <= ADD;
    NO <= '0';     -- Normal operation
    wait for 10 ns;

    -- End simulation
    wait;
  end process;

end architecture;

hardware/hdl/src/alu_tb.vcd
$date
  Sat Sep 21 23:12:25 2024
$end
$version
  GHDL v0
$end
$timescale
  1 fs
$end
$scope module standard $end
$upscope $end
$scope module std_logic_1164 $end
$upscope $end
$scope module numeric_std $end
$upscope $end
$scope module commonpkg $end
$upscope $end
$scope module alu_tb $end
$var reg 16 ! x[15:0] $end
$var reg 16 " y[15:0] $end
$var reg 16 # result[15:0] $end
$var reg 2 $ op[1:0] $end
$var reg 1 % zx $end
$var reg 1 & zy $end
$var reg 1 ' no $end
$var reg 1 ( isneg $end
$var reg 1 ) iszero $end
$scope module uut $end
$var reg 16 * x[15:0] $end
$var reg 16 + y[15:0] $end
$var reg 2 , op[1:0] $end
$var reg 1 - zx $end
$var reg 1 . zy $end
$var reg 1 / no $end
$var reg 16 0 result[15:0] $end
$var reg 1 1 isneg $end
$var reg 1 2 iszero $end
$comment opcode is not handled $end
$var reg 16 3 intermediate_result[15:0] $end
$upscope $end
$upscope $end
$enddefinitions $end
#0
b0000000000000001 !
b0000000000000010 "
b0000000000000011 #
b00 $
0%
0&
0'
0(
0)
b0000000000000001 *
b0000000000000010 +
b00 ,
0-
0.
0/
b0000000000000011 0
01
02
b0000000000000011 3
#10000000
b01 $
b01 ,
#20000000
b1111111111111111 #
b10 $
1(
b10 ,
b1111111111111111 0
11
b1111111111111111 3
#30000000
b0000000000000000 #
b11 $
0(
b11 ,
b0000000000000000 0
01
b0000000000000000 3
#40000000
b0000000000000011 #
b00 $
1%
1)
b00 ,
1-
b0000000000000011 0
12
b0000000000000011 3
#50000000
0%
1&
0)
0-
1.
02
#60000000
1'
1/
#70000000
b0000000000000010 !
b0000000000000100 "
b0000000000000110 #
b01 $
0'
b0000000000000010 *
b0000000000000100 +
b01 ,
0/
b0000000000000110 0
b0000000000000110 3
#80000000
b0000000000000000 !
b0000000000000000 "
b0000000000000000 #
b00 $
b0000000000000000 *
b0000000000000000 +
b00 ,
b0000000000000000 0
b0000000000000000 3
