hardware/hdl/counter.v
module counter(
    input clk,
    input write_en,
    input [15:0] data_in,
    output reg [15:0] data_out
);

initial data_out = 0;

always@(posedge clk)
begin
    if (write_en)
        data_out <= data_in;
    else
        data_out <= data_out + 1;
end

endmodule;

hardware/hdl/counter_tb.v
`timescale 1ns/1ns
`include "counter.v"

module counter_tb;
    reg clk, write_en;
    reg [15:0] data_in;
    wire [15:0] data_out;

    counter uut(
        .clk(clk),
        .write_en(write_en),
        .data_in(data_in),
        .data_out(data_out)
    );

    always begin
        clk = ~clk;
        #5;
    end

    initial
    begin
        $dumpfile("counter.vcd");
        $dumpvars(0, counter_tb);

        clk = 0;
        data_in = 0;
        write_en = 0;
        #80;

        data_in = 15'h20;
        #20;
        write_en = 1;
        #50;
        write_en = 0;
        #200
        data_in = 15'h02;
        write_en = 1;
        #20;
        write_en = 0;
        #200;

        $finish;
    end

endmodule;

hardware/hdl/counter.vcd
$date
	Thu Nov 14 21:52:14 2024
$end
$version
	Icarus Verilog
$end
$timescale
	1ns
$end
$scope module counter_tb $end
$var wire 16 ! data_out [15:0] $end
$var reg 1 " clk $end
$var reg 16 # data_in [15:0] $end
$var reg 1 $ write_en $end
$scope module uut $end
$var wire 1 " clk $end
$var wire 16 % data_in [15:0] $end
$var wire 1 $ write_en $end
$var reg 16 & data_out [15:0] $end
$upscope $end
$upscope $end
$enddefinitions $end
$comment Show the parameter values. $end
$dumpall
$end
#0
$dumpvars
b0 &
b0 %
0$
b0 #
0"
b0 !
$end
#5
b1 !
b1 &
1"
#10
0"
#15
b10 !
b10 &
1"
#20
0"
#25
b11 !
b11 &
1"
#30
0"
#35
b100 !
b100 &
1"
#40
0"
#45
b101 !
b101 &
1"
#50
0"
#55
b110 !
b110 &
1"
#60
0"
#65
b111 !
b111 &
1"
#70
0"
#75
b1000 !
b1000 &
1"
#80
0"
b100000 #
b100000 %
#85
b1001 !
b1001 &
1"
#90
0"
#95
b1010 !
b1010 &
1"
#100
0"
1$
#105
b100000 !
b100000 &
1"
#110
0"
#115
1"
#120
0"
#125
1"
#130
0"
#135
1"
#140
0"
#145
1"
#150
0"
0$
#155
b100001 !
b100001 &
1"
#160
0"
#165
b100010 !
b100010 &
1"
#170
0"
#175
b100011 !
b100011 &
1"
#180
0"
#185
b100100 !
b100100 &
1"
#190
0"
#195
b100101 !
b100101 &
1"
#200
0"
#205
b100110 !
b100110 &
1"
#210
0"
#215
b100111 !
b100111 &
1"
#220
0"
#225
b101000 !
b101000 &
1"
#230
0"
#235
b101001 !
b101001 &
1"
#240
0"
#245
b101010 !
b101010 &
1"
#250
0"
#255
b101011 !
b101011 &
1"
#260
0"
#265
b101100 !
b101100 &
1"
#270
0"
#275
b101101 !
b101101 &
1"
#280
0"
#285
b101110 !
b101110 &
1"
#290
0"
#295
b101111 !
b101111 &
1"
#300
0"
#305
b110000 !
b110000 &
1"
#310
0"
#315
b110001 !
b110001 &
1"
#320
0"
#325
b110010 !
b110010 &
1"
#330
0"
#335
b110011 !
b110011 &
1"
#340
0"
#345
b110100 !
b110100 &
1"
#350
0"
1$
b10 #
b10 %
#355
b10 !
b10 &
1"
#360
0"
#365
1"
#370
0"
0$
#375
b11 !
b11 &
1"
#380
0"
#385
b100 !
b100 &
1"
#390
0"
#395
b101 !
b101 &
1"
#400
0"
#405
b110 !
b110 &
1"
#410
0"
#415
b111 !
b111 &
1"
#420
0"
#425
b1000 !
b1000 &
1"
#430
0"
#435
b1001 !
b1001 &
1"
#440
0"
#445
b1010 !
b1010 &
1"
#450
0"
#455
b1011 !
b1011 &
1"
#460
0"
#465
b1100 !
b1100 &
1"
#470
0"
#475
b1101 !
b1101 &
1"
#480
0"
#485
b1110 !
b1110 &
1"
#490
0"
#495
b1111 !
b1111 &
1"
#500
0"
#505
b10000 !
b10000 &
1"
#510
0"
#515
b10001 !
b10001 &
1"
#520
0"
#525
b10010 !
b10010 &
1"
#530
0"
#535
b10011 !
b10011 &
1"
#540
0"
#545
b10100 !
b10100 &
1"
#550
0"
#555
b10101 !
b10101 &
1"
#560
0"
#565
b10110 !
b10110 &
1"
