hardware/hdl/memory.v
module memory(
    input clk,
    input reset,
    input reg_a_en,
    input reg_d_en,
    input reg_m_en,
    input [15:0] data_in,
    output [15:0] reg_a_out,
    output [15:0] reg_d_out,
    output [15:0] reg_m_out
);

reg [15:0] reg_a=0;
reg [15:0] reg_d=0;

assign reg_a_out = reg_a;
assign reg_d_out = reg_d;
assign reg_m_out = mem[reg_a];

// Declare memory array with block RAM style
//(* ram_style = "block" *) 
reg [15:0] mem [0:8191];

integer i;
initial begin
    for (i = 0; i < 8192; i++) begin
        mem[i] = 0;
    end
end

always@(posedge clk, posedge reset) begin
    if (reset)
    begin
        reg_a <= 16'h0;
        reg_d <= 16'h0;
    end
    else begin
        if (reg_a_en)
            reg_a <= data_in;
        else
            reg_a <= reg_a;

        if (reg_d_en)
            reg_d <= data_in;
        else
            reg_d <= reg_d;

        if (reg_m_en)
            mem[reg_a] <= data_in;
        else
            mem[reg_a] <= mem[reg_a];
    end
end

endmodule;

hardware/hdl/memory_tb.v
`timescale 1ns / 1ps
`include "memory.v"

module memory_tb;

    // Testbench signals
    reg clk;
    reg reg_a_en;
    reg reg_d_en;
    reg reg_m_en;
    reg [15:0] data_in;
    wire [15:0] reg_a_out;
    wire [15:0] reg_d_out;
    wire [15:0] reg_m_out;

    // Instantiate the memory module
    memory uut (
        .clk(clk),
        .reg_a_en(reg_a_en),
        .reg_d_en(reg_d_en),
        .reg_m_en(reg_m_en),
        .data_in(data_in),
        .reg_a_out(reg_a_out),
        .reg_d_out(reg_d_out),
        .reg_m_out(reg_m_out)
    );

    // Clock generation
    always begin
        clk = ~clk;
        #5;
    end
    // Test sequence
    initial begin
        $dumpfile("memory.vcd");
        $dumpvars(0, memory_tb);
        $display("Starting");
        // Initialize inputs
        clk = 0;
        reg_a_en = 0;
        reg_d_en = 0;
        reg_m_en = 0;
        data_in = 0;

        // Display initial values
        $display("Starting test...");

        // Test write to reg_a
        #10;
        data_in = 16'h1234;
        reg_a_en = 1;
        #10;
        reg_a_en = 0;
        #10;
        $display("reg_a_out = %h (expected 1234)", reg_a_out);

        // Test write to reg_d
        #10;
        data_in = 16'h5678;
        reg_d_en = 1;
        #10;
        reg_d_en = 0;
        #10;
        $display("reg_d_out = %h (expected 5678)", reg_d_out);

        // Test write to memory (mem array) at address 0
        #10;
        data_in = 16'h9ABC;
        reg_m_en = 1;
        #10;
        reg_m_en = 0;
        #10;
        $display("reg_m_out at addr 1 = %h (expected 9ABC)", reg_m_out);

        // Test read from memory (mem array) at address 1
        #10;
        $display("Read reg_m_out at addr 1 = %h (expected 9ABC)", reg_m_out);

        // Additional tests if desired...

        $display("Test completed.");
        $finish;
    end

endmodule

hardware/hdl/memory.vcd
$date
	Thu Nov 14 23:06:55 2024
$end
$version
	Icarus Verilog
$end
$timescale
	1ps
$end
$scope module memory_tb $end
$var wire 16 ! reg_m_out [15:0] $end
$var wire 16 " reg_d_out [15:0] $end
$var wire 16 # reg_a_out [15:0] $end
$var reg 1 $ clk $end
$var reg 16 % data_in [15:0] $end
$var reg 1 & reg_a_en $end
$var reg 1 ' reg_d_en $end
$var reg 1 ( reg_m_en $end
$scope module uut $end
$var wire 1 $ clk $end
$var wire 16 ) data_in [15:0] $end
$var wire 1 & reg_a_en $end
$var wire 16 * reg_a_out [15:0] $end
$var wire 1 ' reg_d_en $end
$var wire 16 + reg_d_out [15:0] $end
$var wire 1 ( reg_m_en $end
$var wire 16 , reg_m_out [15:0] $end
$var wire 1 - reset $end
$var reg 16 . reg_a [15:0] $end
$var reg 16 / reg_d [15:0] $end
$var integer 32 0 i [31:0] $end
$upscope $end
$upscope $end
$enddefinitions $end
$comment Show the parameter values. $end
$dumpall
$end
#0
$dumpvars
b10000000000000 0
b0 /
b0 .
z-
b0 ,
b0 +
b0 *
b0 )
0(
0'
0&
b0 %
0$
b0 #
b0 "
b0 !
$end
#5000
1$
#10000
0$
1&
b1001000110100 %
b1001000110100 )
#15000
b1001000110100 #
b1001000110100 *
b1001000110100 .
1$
#20000
0$
0&
#25000
1$
#30000
0$
#35000
1$
#40000
0$
1'
b101011001111000 %
b101011001111000 )
#45000
b101011001111000 "
b101011001111000 +
b101011001111000 /
1$
#50000
0$
0'
#55000
1$
#60000
0$
#65000
1$
#70000
0$
1(
b1001101010111100 %
b1001101010111100 )
#75000
b1001101010111100 !
b1001101010111100 ,
1$
#80000
0$
0(
