hardware/hdl/rom.v
module rom(
    input wire [7:0] address,
    output [15:0] data
);
    reg [15:0] rom_memory [0:255];
    assign data = rom_memory[address];

    initial $readmemh("program.txt", rom_memory);
endmodule;

hardware/hdl/rom_tb.v
`timescale 1ns/1ns
`include "rom.v"

module rom_tb;
    reg [7:0] address;
    wire [15:0] data;

    rom uut (
        .address(address),
        .data(data)
    );

    initial
    begin
        $dumpfile("rom.vcd");
        $dumpvars(0, rom_tb);

        $display("Checking rom");

        for (address = 0; address < 10; address++) begin
            #100;
            $display("Address %h = %h", address, data);
        end
        $display("Done");

        $finish;
    end
endmodule;

hardware/hdl/rom.vcd
$date
	Thu Nov 14 22:16:30 2024
$end
$version
	Icarus Verilog
$end
$timescale
	1ns
$end
$scope module rom_tb $end
$var wire 16 ! data [15:0] $end
$var reg 8 " address [7:0] $end
$scope module uut $end
$var wire 8 # address [7:0] $end
$var wire 16 $ data [15:0] $end
$upscope $end
$upscope $end
$enddefinitions $end
$comment Show the parameter values. $end
$dumpall
$end
#0
$dumpvars
b1000000000001111 $
b0 #
b0 "
b1000000000001111 !
$end
#100
b10000001000000 !
b10000001000000 $
b1 "
b1 #
#200
b10011100000000 !
b10011100000000 $
b10 "
b10 #
#300
b1000000000000000 !
b1000000000000000 $
b11 "
b11 #
#400
bx !
bx $
b100 "
b100 #
#500
b101 "
b101 #
#600
b110 "
b110 #
#700
b111 "
b111 #
#800
b1000 "
b1000 #
#900
b1001 "
b1001 #
#1000
b1010 "
b1010 #
