hardware/hdl/rom.v
module rom(
    input wire [7:0] address,
    output [15:0] data
);
    reg [15:0] rom_memory [0:255];
    assign data = rom_memory[address];

    initial $readmemh("program.txt", rom_memory);
endmodule;

hardware/hdl/counter.v
module counter(
    input clk,
    input write_en,
    input [15:0] data_in,
    output reg [15:0] data_out
);

initial data_out = 0;

always@(posedge clk)
begin
    if (write_en)
        data_out <= data_in;
    else
        data_out <= data_out + 1;
end

endmodule;

hardware/hdl/control_unit.v
module control_unit(
    input [15:0] instr,
    input [15:0] reg_a_in, reg_d_in, reg_m_in,
    input is_negative, is_zero,
    output [15:0] addr_out,
    output instr_type,
    output reg_a_en, reg_d_en, reg_m_en,
    output set_pc,
    output [15:0] x, y,
    output [1:0] opcode,
    output negate_output, zero_x, zero_y
);
    wire [3:0] reg_selects;
    wire [2:0] dest_selects;
    wire [2:0] flags;
    wire [2:0] jump_condition;

    // instruction decoding
    assign jump_condition = instr[2:0];
    assign opcode = instr[4:3];
    assign flags = instr[7:5];
    assign reg_selects = instr[11:8];
    assign dest_selects = instr[14:12];
    assign instr_type = instr[15];
    assign addr_out = { 1'b0, instr[14:0] };

    assign reg_m_en = dest_selects[0];
    assign reg_d_en = dest_selects[1];
    assign reg_a_en = dest_selects[2] | instr_type;

    assign negate_output = flags[0];
    assign zero_y = flags[1];
    assign zero_x = flags[2];

    assign set_pc = ~instr_type & (
        (jump_condition == 3'h0) & 0 |
        (jump_condition == 3'h1) & ~is_negative |
        (jump_condition == 3'h2) & is_zero |
        (jump_condition == 3'h3) & (~is_negative | is_zero) |
        (jump_condition == 3'h4) & (is_negative) |
        (jump_condition == 3'h5) & (~is_zero) |
        (jump_condition == 3'h6) & (is_zero | is_negative) |
        (jump_condition == 3'h7) & 1
    );

    assign x = ( reg_selects[1:0] == 2'h0 ) ? reg_a_in : (
        (reg_selects[1:0] == 2'h1) ? reg_d_in : (
            (reg_selects[1:0] == 2'h2) ? reg_m_in : 16'h1
        )
    );

    assign y = ( reg_selects[3:2] == 2'h0 ) ? reg_a_in : (
        (reg_selects[3:2] == 2'h1) ? reg_d_in : (
            (reg_selects[3:2] == 2'h2) ? reg_m_in : 16'h1
        )
    );

endmodule;

hardware/hdl/memory.v
module memory(
    input clk,
    input reg_a_en,
    input reg_d_en,
    input reg_m_en,
    input [15:0] data_in,
    output [15:0] reg_a_out,
    output [15:0] reg_d_out,
    output [15:0] reg_m_out
);

reg [15:0] reg_a;
reg [15:0] reg_d;

assign reg_a_out = reg_a;
assign reg_d_out = reg_d;
assign reg_m_out = mem[reg_a];

// Declare memory array with block RAM style
(* ram_style = "block" *) reg [15:0] mem [0:8191];

always@(posedge clk) begin
    if (reg_a_en)
        reg_a <= data_in;
    else
        reg_a <= reg_a;

    if (reg_d_en)
        reg_d <= data_in;
    else
        reg_d <= reg_d;

    if (reg_m_en)
        mem[reg_a] <= data_in;
    else
        mem[reg_a] <= mem[reg_a];
end

endmodule;

hardware/hdl/alu.v
module alu(
    input [15:0] x, y,
    input zero_x, zero_y, negate_output, clk,
    input [1:0] opcode,
    output wire [15:0] output_result,
    output is_zero, is_negative
);

wire [15:0] effective_x, effective_y;

reg [15:0] internal_output;

assign effective_x = (zero_x) ? 16'h0000 : x;
assign effective_y = (zero_y) ? 16'h0000 : y;

assign output_result = (negate_output) ? ~internal_output : internal_output;
assign is_zero = (internal_output == 16'h0000) ? 1 : 0;
assign is_negative = output_result[15];

localparam OPCODE_OR  = 2'h0;
localparam OPCODE_AND = 2'h1;
localparam OPCODE_ADD = 2'h2;
localparam OPCODE_SUB = 2'h3;

always@(posedge clk)
begin
    case (opcode)
        OPCODE_OR:  internal_output = effective_x | effective_y;
        OPCODE_AND: internal_output = effective_x & effective_y;
        OPCODE_ADD: internal_output = effective_x + effective_y;
        OPCODE_SUB: internal_output = effective_x - effective_y;
         default: internal_output = 16'h00;
    endcase
end

endmodule;

hardware/hdl/top.v
`include "counter.v"
`include "rom.v"
`include "memory.v"
`include "alu.v"
`include "control_unit.v"

module top(
    input clk
);

    wire [15:0] alu_out, addr_const;
    wire instr_type, set_pc;
    wire [15:0] x, y, instr, reg_a, reg_d, reg_m;
    wire [1:0] opcode;
    wire zero_x, zero_y, negate_output, is_negative, is_zero;
    wire dest_a, dest_d, dest_m;

    wire [15:0] pc;

    alu alu(
        .clk(clk),
        .x(x),
        .y(y),
        .zero_x(zero_x),
        .zero_y(zero_y),
        .negate_output(negate_output),
        .opcode(opcode),
        .output_result(alu_out),
        .is_zero(is_zero),
        .is_negative(is_negative)
    );

    memory memory(
        .clk(clk),
        .reg_a_en(dest_a),
        .reg_d_en(dest_d),
        .reg_m_en(dest_m),
        .data_in(
            (instr_type) ? addr_const : alu_out
        ),
        .reg_a_out(reg_a),
        .reg_d_out(reg_d),
        .reg_m_out(reg_m)
    );

    control_unit control_unit(
        .instr(instr),
        .reg_a_in(reg_a),
        .reg_d_in(reg_d),
        .reg_m_in(reg_m),
        .is_negative(is_negative),
        .is_zero(is_zero),
        .addr_out(addr_const),
        .instr_type(instr_type),
        .reg_a_en(dest_a),
        .reg_d_en(dest_d),
        .reg_m_en(dest_m),
        .set_pc(set_pc),
        .x(x),
        .y(y),
        .opcode(opcode),
        .negate_output(negate_output),
        .zero_x(zero_x),
        .zero_y(zero_y)
    );

    counter counter(
        .clk(clk),
        .write_en(set_pc),
        .data_in(
            (instr_type) ? addr_const : alu_out
        ),
        .data_out(pc)
    );

    rom rom (
        .address(pc[7:0]),
        .data(instr)
    );

endmodule;

hardware/hdl/top_tb.v
`timescale 1ns / 1ns
`include "top.v"

module top_tb;
    reg clk;

    top top(.clk(clk));

    always
    begin
        clk = ~clk;
        #5;
    end

    initial begin
        $dumpfile("top.vcd");
        $dumpvars(0, top_tb);
        clk = 0;
        #500
        $finish;
    end
endmodule;

hardware/hdl/top.vcd
$date
	Thu Nov 14 22:43:04 2024
$end
$version
	Icarus Verilog
$end
$timescale
	1ns
$end
$scope module top_tb $end
$var reg 1 ! clk $end
$scope module top $end
$var wire 1 ! clk $end
$var wire 1 " zero_y $end
$var wire 1 # zero_x $end
$var wire 16 $ y [15:0] $end
$var wire 16 % x [15:0] $end
$var wire 1 & set_pc $end
$var wire 16 ' reg_m [15:0] $end
$var wire 16 ( reg_d [15:0] $end
$var wire 16 ) reg_a [15:0] $end
$var wire 16 * pc [15:0] $end
$var wire 2 + opcode [1:0] $end
$var wire 1 , negate_output $end
$var wire 1 - is_zero $end
$var wire 1 . is_negative $end
$var wire 1 / instr_type $end
$var wire 16 0 instr [15:0] $end
$var wire 1 1 dest_m $end
$var wire 1 2 dest_d $end
$var wire 1 3 dest_a $end
$var wire 16 4 alu_out [15:0] $end
$var wire 16 5 addr_const [15:0] $end
$scope module alu $end
$var wire 1 ! clk $end
$var wire 1 " zero_y $end
$var wire 1 # zero_x $end
$var wire 16 6 y [15:0] $end
$var wire 16 7 x [15:0] $end
$var wire 16 8 output_result [15:0] $end
$var wire 2 9 opcode [1:0] $end
$var wire 1 , negate_output $end
$var wire 1 - is_zero $end
$var wire 1 . is_negative $end
$var wire 16 : effective_y [15:0] $end
$var wire 16 ; effective_x [15:0] $end
$var parameter 2 < OPCODE_ADD $end
$var parameter 2 = OPCODE_AND $end
$var parameter 2 > OPCODE_OR $end
$var parameter 2 ? OPCODE_SUB $end
$var reg 16 @ internal_output [15:0] $end
$upscope $end
$scope module control_unit $end
$var wire 1 . is_negative $end
$var wire 1 - is_zero $end
$var wire 1 3 reg_a_en $end
$var wire 1 " zero_y $end
$var wire 1 # zero_x $end
$var wire 1 & set_pc $end
$var wire 4 A reg_selects [3:0] $end
$var wire 16 B reg_m_in [15:0] $end
$var wire 1 1 reg_m_en $end
$var wire 16 C reg_d_in [15:0] $end
$var wire 1 2 reg_d_en $end
$var wire 16 D reg_a_in [15:0] $end
$var wire 2 E opcode [1:0] $end
$var wire 1 , negate_output $end
$var wire 3 F jump_condition [2:0] $end
$var wire 1 / instr_type $end
$var wire 16 G instr [15:0] $end
$var wire 3 H flags [2:0] $end
$var wire 3 I dest_selects [2:0] $end
$var wire 16 J addr_out [15:0] $end
$var reg 16 K x [15:0] $end
$var reg 16 L y [15:0] $end
$upscope $end
$scope module counter $end
$var wire 1 ! clk $end
$var wire 16 M data_in [15:0] $end
$var wire 1 & write_en $end
$var reg 16 N data_out [15:0] $end
$upscope $end
$scope module memory $end
$var wire 1 ! clk $end
$var wire 16 O data_in [15:0] $end
$var wire 1 3 reg_a_en $end
$var wire 16 P reg_a_out [15:0] $end
$var wire 1 2 reg_d_en $end
$var wire 16 Q reg_d_out [15:0] $end
$var wire 1 1 reg_m_en $end
$var wire 16 R reg_m_out [15:0] $end
$var reg 16 S reg_a [15:0] $end
$var reg 16 T reg_d [15:0] $end
$upscope $end
$scope module rom $end
$var wire 8 U address [7:0] $end
$var wire 16 V data [15:0] $end
$upscope $end
$upscope $end
$upscope $end
$enddefinitions $end
$comment Show the parameter values. $end
$dumpall
b11 ?
b0 >
b1 =
b10 <
$end
#0
$dumpvars
b1000000000000001 V
b0 U
bx T
bx S
bx R
bx Q
bx P
b1 O
b0 N
b1 M
bx L
bx K
b1 J
b0 I
b0 H
b1000000000000001 G
b1 F
b0 E
bx D
bx C
bx B
b0 A
bx @
bx ;
bx :
b0 9
bx 8
bx 7
bx 6
b1 5
bx 4
13
02
01
b1000000000000001 0
1/
x.
x-
0,
b0 +
b0 *
bx )
bx (
bx '
0&
bx %
bx $
0#
0"
0!
$end
#5
0&
03
bx M
bx O
12
1"
b0 :
b1 ;
b10001101000000 5
b10001101000000 J
0/
b10 I
b11 A
b10 H
b0 F
b1 $
b1 6
b1 L
b1 %
b1 7
b1 K
b10001101000000 0
b10001101000000 G
b10001101000000 V
b1 U
b1 )
b1 D
b1 P
b1 S
b1 *
b1 N
1!
#10
0!
#15
1&
02
bx $
bx 6
bx L
b101101000111 5
b101101000111 J
b0 I
b1011 A
b111 F
b101101000111 0
b101101000111 G
b101101000111 V
b10 U
b10 *
b10 N
0.
b1 M
b1 O
0-
b1 4
b1 8
b1 @
1!
#20
0!
#25
0&
12
b1 $
b1 6
b1 L
b10001101000000 5
b10001101000000 J
b10 I
b11 A
b0 F
b10001101000000 0
b10001101000000 G
b10001101000000 V
b1 U
b1 *
b1 N
1!
#30
0!
#35
1&
02
bx $
bx 6
bx L
b101101000111 5
b101101000111 J
b0 I
b1011 A
b111 F
b101101000111 0
b101101000111 G
b101101000111 V
b10 U
b10 *
b10 N
b1 (
b1 C
b1 Q
b1 T
1!
#40
0!
#45
0&
12
b1 $
b1 6
b1 L
b10001101000000 5
b10001101000000 J
b10 I
b11 A
b0 F
b10001101000000 0
b10001101000000 G
b10001101000000 V
b1 U
b1 *
b1 N
1!
#50
0!
#55
1&
02
bx $
bx 6
bx L
b101101000111 5
b101101000111 J
b0 I
b1011 A
b111 F
b101101000111 0
b101101000111 G
b101101000111 V
b10 U
b10 *
b10 N
1!
#60
0!
#65
0&
12
b1 $
b1 6
b1 L
b10001101000000 5
b10001101000000 J
b10 I
b11 A
b0 F
b10001101000000 0
b10001101000000 G
b10001101000000 V
b1 U
b1 *
b1 N
1!
#70
0!
#75
1&
02
bx $
bx 6
bx L
b101101000111 5
b101101000111 J
b0 I
b1011 A
b111 F
b101101000111 0
b101101000111 G
b101101000111 V
b10 U
b10 *
b10 N
1!
#80
0!
#85
0&
12
b1 $
b1 6
b1 L
b10001101000000 5
b10001101000000 J
b10 I
b11 A
b0 F
b10001101000000 0
b10001101000000 G
b10001101000000 V
b1 U
b1 *
b1 N
1!
#90
0!
#95
1&
02
bx $
bx 6
bx L
b101101000111 5
b101101000111 J
b0 I
b1011 A
b111 F
b101101000111 0
b101101000111 G
b101101000111 V
b10 U
b10 *
b10 N
1!
#100
0!
#105
0&
12
b1 $
b1 6
b1 L
b10001101000000 5
b10001101000000 J
b10 I
b11 A
b0 F
b10001101000000 0
b10001101000000 G
b10001101000000 V
b1 U
b1 *
b1 N
1!
#110
0!
#115
1&
02
bx $
bx 6
bx L
b101101000111 5
b101101000111 J
b0 I
b1011 A
b111 F
b101101000111 0
b101101000111 G
b101101000111 V
b10 U
b10 *
b10 N
1!
#120
0!
#125
0&
12
b1 $
b1 6
b1 L
b10001101000000 5
b10001101000000 J
b10 I
b11 A
b0 F
b10001101000000 0
b10001101000000 G
b10001101000000 V
b1 U
b1 *
b1 N
1!
#130
0!
#135
1&
02
bx $
bx 6
bx L
b101101000111 5
b101101000111 J
b0 I
b1011 A
b111 F
b101101000111 0
b101101000111 G
b101101000111 V
b10 U
b10 *
b10 N
1!
#140
0!
#145
0&
12
b1 $
b1 6
b1 L
b10001101000000 5
b10001101000000 J
b10 I
b11 A
b0 F
b10001101000000 0
b10001101000000 G
b10001101000000 V
b1 U
b1 *
b1 N
1!
#150
0!
#155
1&
02
bx $
bx 6
bx L
b101101000111 5
b101101000111 J
b0 I
b1011 A
b111 F
b101101000111 0
b101101000111 G
b101101000111 V
b10 U
b10 *
b10 N
1!
#160
0!
#165
0&
12
b1 $
b1 6
b1 L
b10001101000000 5
b10001101000000 J
b10 I
b11 A
b0 F
b10001101000000 0
b10001101000000 G
b10001101000000 V
b1 U
b1 *
b1 N
1!
#170
0!
#175
1&
02
bx $
bx 6
bx L
b101101000111 5
b101101000111 J
b0 I
b1011 A
b111 F
b101101000111 0
b101101000111 G
b101101000111 V
b10 U
b10 *
b10 N
1!
#180
0!
#185
0&
12
b1 $
b1 6
b1 L
b10001101000000 5
b10001101000000 J
b10 I
b11 A
b0 F
b10001101000000 0
b10001101000000 G
b10001101000000 V
b1 U
b1 *
b1 N
1!
#190
0!
#195
1&
02
bx $
bx 6
bx L
b101101000111 5
b101101000111 J
b0 I
b1011 A
b111 F
b101101000111 0
b101101000111 G
b101101000111 V
b10 U
b10 *
b10 N
1!
#200
0!
#205
0&
12
b1 $
b1 6
b1 L
b10001101000000 5
b10001101000000 J
b10 I
b11 A
b0 F
b10001101000000 0
b10001101000000 G
b10001101000000 V
b1 U
b1 *
b1 N
1!
#210
0!
#215
1&
02
bx $
bx 6
bx L
b101101000111 5
b101101000111 J
b0 I
b1011 A
b111 F
b101101000111 0
b101101000111 G
b101101000111 V
b10 U
b10 *
b10 N
1!
#220
0!
#225
0&
12
b1 $
b1 6
b1 L
b10001101000000 5
b10001101000000 J
b10 I
b11 A
b0 F
b10001101000000 0
b10001101000000 G
b10001101000000 V
b1 U
b1 *
b1 N
1!
#230
0!
#235
1&
02
bx $
bx 6
bx L
b101101000111 5
b101101000111 J
b0 I
b1011 A
b111 F
b101101000111 0
b101101000111 G
b101101000111 V
b10 U
b10 *
b10 N
1!
#240
0!
#245
0&
12
b1 $
b1 6
b1 L
b10001101000000 5
b10001101000000 J
b10 I
b11 A
b0 F
b10001101000000 0
b10001101000000 G
b10001101000000 V
b1 U
b1 *
b1 N
1!
#250
0!
#255
1&
02
bx $
bx 6
bx L
b101101000111 5
b101101000111 J
b0 I
b1011 A
b111 F
b101101000111 0
b101101000111 G
b101101000111 V
b10 U
b10 *
b10 N
1!
#260
0!
#265
0&
12
b1 $
b1 6
b1 L
b10001101000000 5
b10001101000000 J
b10 I
b11 A
b0 F
b10001101000000 0
b10001101000000 G
b10001101000000 V
b1 U
b1 *
b1 N
1!
#270
0!
#275
1&
02
bx $
bx 6
bx L
b101101000111 5
b101101000111 J
b0 I
b1011 A
b111 F
b101101000111 0
b101101000111 G
b101101000111 V
b10 U
b10 *
b10 N
1!
#280
0!
#285
0&
12
b1 $
b1 6
b1 L
b10001101000000 5
b10001101000000 J
b10 I
b11 A
b0 F
b10001101000000 0
b10001101000000 G
b10001101000000 V
b1 U
b1 *
b1 N
1!
#290
0!
#295
1&
02
bx $
bx 6
bx L
b101101000111 5
b101101000111 J
b0 I
b1011 A
b111 F
b101101000111 0
b101101000111 G
b101101000111 V
b10 U
b10 *
b10 N
1!
#300
0!
#305
0&
12
b1 $
b1 6
b1 L
b10001101000000 5
b10001101000000 J
b10 I
b11 A
b0 F
b10001101000000 0
b10001101000000 G
b10001101000000 V
b1 U
b1 *
b1 N
1!
#310
0!
#315
1&
02
bx $
bx 6
bx L
b101101000111 5
b101101000111 J
b0 I
b1011 A
b111 F
b101101000111 0
b101101000111 G
b101101000111 V
b10 U
b10 *
b10 N
1!
#320
0!
#325
0&
12
b1 $
b1 6
b1 L
b10001101000000 5
b10001101000000 J
b10 I
b11 A
b0 F
b10001101000000 0
b10001101000000 G
b10001101000000 V
b1 U
b1 *
b1 N
1!
#330
0!
#335
1&
02
bx $
bx 6
bx L
b101101000111 5
b101101000111 J
b0 I
b1011 A
b111 F
b101101000111 0
b101101000111 G
b101101000111 V
b10 U
b10 *
b10 N
1!
#340
0!
#345
0&
12
b1 $
b1 6
b1 L
b10001101000000 5
b10001101000000 J
b10 I
b11 A
b0 F
b10001101000000 0
b10001101000000 G
b10001101000000 V
b1 U
b1 *
b1 N
1!
#350
0!
#355
1&
02
bx $
bx 6
bx L
b101101000111 5
b101101000111 J
b0 I
b1011 A
b111 F
b101101000111 0
b101101000111 G
b101101000111 V
b10 U
b10 *
b10 N
1!
#360
0!
#365
0&
12
b1 $
b1 6
b1 L
b10001101000000 5
b10001101000000 J
b10 I
b11 A
b0 F
b10001101000000 0
b10001101000000 G
b10001101000000 V
b1 U
b1 *
b1 N
1!
#370
0!
#375
1&
02
bx $
bx 6
bx L
b101101000111 5
b101101000111 J
b0 I
b1011 A
b111 F
b101101000111 0
b101101000111 G
b101101000111 V
b10 U
b10 *
b10 N
1!
#380
0!
#385
0&
12
b1 $
b1 6
b1 L
b10001101000000 5
b10001101000000 J
b10 I
b11 A
b0 F
b10001101000000 0
b10001101000000 G
b10001101000000 V
b1 U
b1 *
b1 N
1!
#390
0!
#395
1&
02
bx $
bx 6
bx L
b101101000111 5
b101101000111 J
b0 I
b1011 A
b111 F
b101101000111 0
b101101000111 G
b101101000111 V
b10 U
b10 *
b10 N
1!
#400
0!
#405
0&
12
b1 $
b1 6
b1 L
b10001101000000 5
b10001101000000 J
b10 I
b11 A
b0 F
b10001101000000 0
b10001101000000 G
b10001101000000 V
b1 U
b1 *
b1 N
1!
#410
0!
#415
1&
02
bx $
bx 6
bx L
b101101000111 5
b101101000111 J
b0 I
b1011 A
b111 F
b101101000111 0
b101101000111 G
b101101000111 V
b10 U
b10 *
b10 N
1!
#420
0!
#425
0&
12
b1 $
b1 6
b1 L
b10001101000000 5
b10001101000000 J
b10 I
b11 A
b0 F
b10001101000000 0
b10001101000000 G
b10001101000000 V
b1 U
b1 *
b1 N
1!
#430
0!
#435
1&
02
bx $
bx 6
bx L
b101101000111 5
b101101000111 J
b0 I
b1011 A
b111 F
b101101000111 0
b101101000111 G
b101101000111 V
b10 U
b10 *
b10 N
1!
#440
0!
#445
0&
12
b1 $
b1 6
b1 L
b10001101000000 5
b10001101000000 J
b10 I
b11 A
b0 F
b10001101000000 0
b10001101000000 G
b10001101000000 V
b1 U
b1 *
b1 N
1!
#450
0!
#455
1&
02
bx $
bx 6
bx L
b101101000111 5
b101101000111 J
b0 I
b1011 A
b111 F
b101101000111 0
b101101000111 G
b101101000111 V
b10 U
b10 *
b10 N
1!
#460
0!
#465
0&
12
b1 $
b1 6
b1 L
b10001101000000 5
b10001101000000 J
b10 I
b11 A
b0 F
b10001101000000 0
b10001101000000 G
b10001101000000 V
b1 U
b1 *
b1 N
1!
#470
0!
#475
1&
02
bx $
bx 6
bx L
b101101000111 5
b101101000111 J
b0 I
b1011 A
b111 F
b101101000111 0
b101101000111 G
b101101000111 V
b10 U
b10 *
b10 N
1!
#480
0!
#485
0&
12
b1 $
b1 6
b1 L
b10001101000000 5
b10001101000000 J
b10 I
b11 A
b0 F
b10001101000000 0
b10001101000000 G
b10001101000000 V
b1 U
b1 *
b1 N
1!
#490
0!
#495
1&
02
bx $
bx 6
bx L
b101101000111 5
b101101000111 J
b0 I
b1011 A
b111 F
b101101000111 0
b101101000111 G
b101101000111 V
b10 U
b10 *
b10 N
1!
